phixpy/__init__.py
phixpy/backend/__init__.py
phixpy/backend/compressor/__init__.py
phixpy/backend/compressor/compressor.py
phixpy/backend/math_funcs_utils/__init__.py
phixpy/backend/math_funcs_utils/math_funcs.py
phixpy/backend/math_funcs_utils/uid.py
phixpy/backend/math_funcs_utils/utils.py
phixpy/backend/vector/__init__.py
phixpy/backend/vector/vector.py
phixpy/backend/visualization/__init__.py
phixpy/backend/visualization/vector_plot.py
phixpy-0.1.0.dist-info/METADATA
phixpy-0.1.0.dist-info/WHEEL
phixpy-0.1.0.dist-info/top_level.txt
phixpy-0.1.0.dist-info/RECORD
