Metadata-Version: 2.1
Name: phixpy
Version: 0.1.0
Summary: A package for physics operation (currently only for vector operation)
Author: Rijul Dhungana
Author-email: rijuldhungana37@gmail.com
Keywords: phixpy,physics,vectors,science,physics-python
Classifier: Development Status :: 3 - Alpha
Classifier: Intended Audience :: Developers
Classifier: Programming Language :: Python :: 3
Classifier: Topic :: Utilities
Requires-Python: >=3.7
Requires-Dist: numpy
Requires-Dist: matplotlib
